{
	"configurations" : 
	[
		{
			"directories" : 
			[
				{
					"build" : ".",
					"jsonFile" : "directory-.-Debug-d0094a50bb2071803777.json",
					"minimumCMakeVersion" : 
					{
						"string" : "3.29"
					},
					"projectIndex" : 0,
					"source" : ".",
					"targetIndexes" : 
					[
						0,
						1,
						2,
						3
					]
				}
			],
			"name" : "Debug",
			"projects" : 
			[
				{
					"directoryIndexes" : 
					[
						0
					],
					"name" : "Elementwise",
					"targetIndexes" : 
					[
						0,
						1,
						2,
						3
					]
				}
			],
			"targets" : 
			[
				{
					"directoryIndex" : 0,
					"id" : "upsamplenearest_v1::@6890427a1f51a3e7e1df",
					"jsonFile" : "target-upsamplenearest_v1-Debug-751a3ec8fb481bd46cc9.json",
					"name" : "upsamplenearest_v1",
					"projectIndex" : 0
				},
				{
					"directoryIndex" : 0,
					"id" : "upsamplenearest_v2::@6890427a1f51a3e7e1df",
					"jsonFile" : "target-upsamplenearest_v2-Debug-ba229a8bf870df7c06e0.json",
					"name" : "upsamplenearest_v2",
					"projectIndex" : 0
				},
				{
					"directoryIndex" : 0,
					"id" : "upsamplenearest_v3::@6890427a1f51a3e7e1df",
					"jsonFile" : "target-upsamplenearest_v3-Debug-148366a99092df42d1b9.json",
					"name" : "upsamplenearest_v3",
					"projectIndex" : 0
				},
				{
					"directoryIndex" : 0,
					"id" : "upsamplenearest_v4::@6890427a1f51a3e7e1df",
					"jsonFile" : "target-upsamplenearest_v4-Debug-ee8e1b52df689d84e75e.json",
					"name" : "upsamplenearest_v4",
					"projectIndex" : 0
				}
			]
		}
	],
	"kind" : "codemodel",
	"paths" : 
	{
		"build" : "D:/CUDA-Optimization-main/UpsampleNearst/cmake-build-debug",
		"source" : "D:/CUDA-Optimization-main/UpsampleNearst"
	},
	"version" : 
	{
		"major" : 2,
		"minor" : 7
	}
}
